Workbook

Sheet Top 20 Ranking
A1: Final Rank | B1: Name | C1: City | D1: Year Founded | E1: Type | F1: Website URL | G1: Startups supported (as reported) | H1: Startups figure used (cumulative) | I1: Years operating | J1: Startups per year | K1: Rank – Method 1 (cumulative scale) | L1: Rank – Method 2 (annual throughput) | M1: Average of the two ranks | N1: In Top 20? | O1: Funding (as reported) | P1: Description | Q1: Data note | R1: Source
A2: =COUNTIF($M$2:$M$25,"<"&M2)+COUNTIFS($M$2:$M$25,M2,$K$2:$K$25,"<"&K2)+1 -> 1 | B2: Kerala Startup Mission (KSUM) | C2: Thiruvananthapuram | D2: 2006 | E2: Government agency | F2: https://startupmission.kerala.gov.in/ | G2: 8,000+ registered startups supported as of 2025 (directory listing). | H2: 8000 | I2: 20 | J2: =H2/I2 -> 400 | K2: =RANK(H2,$H$2:$H$25,0) -> 1 | L2: =RANK(J2,$J$2:$J$25,0) -> 1 | M2: =AVERAGE(K2,L2) -> 1 | N2: =IF(A2<=20,"Yes","No") -> Yes | O2: Over $665 million facilitated (same listing). KSUM’s own equity investments crossed $12.1 million. | P2: Nodal Agency for Entrepreneurship & Incubation of the Government of Kerala – Technology Start-up Policy of the State. | Q2: Years operating corrected to 20 (founded 2006); the research sheet had 10. Figure is "registered startups" on the state platform, not strictly incubated; it is the most generous count in the list. | R2: https://startupmission.kerala.gov.in./
A3: =COUNTIF($M$2:$M$25,"<"&M3)+COUNTIFS($M$2:$M$25,M3,$K$2:$K$25,"<"&K3)+1 -> 2 | B3: NSRCEL (IIM Bangalore) | C3: Bengaluru | D3: 2000 | E3: University (IIM Bangalore), government-recognised | F3: https://nsrcel.org/ | G3: 3,222+ ventures incubated (a figure reported in a 2026 HDFC Life press release) | H3: 3222 | I3: 26 | J3: =H3/I3 -> 123.92308 | K3: =RANK(H3,$H$2:$H$25,0) -> 2 | L3: =RANK(J3,$J$2:$J$25,0) -> 3 | M3: =AVERAGE(K3,L3) -> 2.5 | N3: =IF(A3<=20,"Yes","No") -> Yes | O3: ₹134 Cr+ (funding raised by incubated ventures in FY 2024–25) | P3: IIMB incubation and entrepreneurship center. This has been recognized by the Government of India, started in 2000, and is backed by SIDBI, NITI Aayog, DST, and MeitY. It operates Women, Social Venture, and Sectorial programs. | Q3: 3,222 ventures per a 2026 press release; includes programme participants, not only residents. | R3: https://www.hdfclife.com/content/dam/hdfclifeinsurancecompany/about-us/pdf/media-centre/press-release/2026/May-2026/press-release-futurance-7-may-2026.pdf?srsltid=AU7gw4XzT5Q6HRtEs03VclAnbBgOjH2Z2T5vPYpehbQERy975WinJGi7
A4: =COUNTIF($M$2:$M$25,"<"&M4)+COUNTIFS($M$2:$M$25,M4,$K$2:$K$25,"<"&K4)+1 -> 3 | B4: T-Hub | C4: Hyderabad | D4: 2015 | E4: Government-backed PPP | F4: https://www.t-hub.co/ | G4: More than 2,000 over nine years (CEO, YourStory, Aug 2024). 2,300+ per a directory listing (undated). | H4: 2000 | I4: 11 | J4: =H4/I4 -> 181.81818 | K4: =RANK(H4,$H$2:$H$25,0) -> 3 | L4: =RANK(J4,$J$2:$J$25,0) -> 2 | M4: =AVERAGE(K4,L4) -> 2.5 | N4: =IF(A4<=20,"Yes","No") -> Yes | O4: About $2.5 billion cumulative (YourStory, Aug 2024). $2B+ per the directory listing. | P4: A government-backed innovation campus that runs incubation, acceleration, corporate-partnership and international soft-landing programmes. It was set up in 2015 as a public-private partnership between the Government of Telangana, IIIT Hyderabad, ISB and NALSAR | Q4: 2,000+ per CEO (Aug 2024); a directory lists 2,300+ (undated). The dated, lower figure is used. | R4: https://yourstory.com/2025/08/t-hub-rolls-out-fourth-cohort-of-charge-with-21-mobility-startups
A5: =COUNTIF($M$2:$M$25,"<"&M5)+COUNTIFS($M$2:$M$25,M5,$K$2:$K$25,"<"&K5)+1 -> 4 | B5: Zone Startups India | C5: Mumbai | D5: 2014 | E5: University/Exchange joint venture | F5: https://www.zonestartups.com/ | G5: Over 600 supported in nine years | H5: 600 | I5: 12 | J5: =H5/I5 -> 50 | K5: =RANK(H5,$H$2:$H$25,0) -> 5 | L5: =RANK(J5,$J$2:$J$25,0) -> 4 | M5: =AVERAGE(K5,L5) -> 4.5 | N5: =IF(A5<=20,"Yes","No") -> Yes | O5: ₹2,400+ crore raised by supported startups | P5: A Mumbai accelerator at the BSE building. It is part of a not-for-profit foundation set up by BSE Institute, Toronto Metropolitan University and Simon Fraser University. | Q5: "Over 600 supported in nine years" (older figure) over 12 years of operation: understates current throughput. | R5: https://www.zonestartups.com/
A6: =COUNTIF($M$2:$M$25,"<"&M6)+COUNTIFS($M$2:$M$25,M6,$K$2:$K$25,"<"&K6)+1 -> 5 | B6: CIIE.CO (IIM Ahmedabad; now IIMA Ventures) | C6: Ahmedabad | D6: 2002 | E6: University(IIM Ahmedabad) with Government of India (DST) and Gujarat government support. | F6: https://iimaventures.com/ | G6: Over 1,000 accelerated, over 300 funded, and over 5,000 mentored or coached. | H6: 1000 | I6: 24 | J6: =H6/I6 -> 41.666667 | K6: =RANK(H6,$H$2:$H$25,0) -> 4 | L6: =RANK(J6,$J$2:$J$25,0) -> 7 | M6: =AVERAGE(K6,L6) -> 5.5 | N6: =IF(A6<=20,"Yes","No") -> Yes | O6: Portfolio companies have raised over $3 billion in follow-on capital, and 400+ startups were invested in (aggregator listing). | P6: Incubation, Acceleration & Seed Fund Platform at IIM-A. Founded in 2002 as an entrepreneurship center and started its Technology Business Incubator in 2007-08, it is a Center of Excellence supported by DST & Government of Gujarat. | Q6: 1,000 = "accelerated"; the 5,000+ mentored/coached figure is not used. | R6: https://iimaventures.com/
A7: =COUNTIF($M$2:$M$25,"<"&M7)+COUNTIFS($M$2:$M$25,M7,$K$2:$K$25,"<"&K7)+1 -> 6 | B7: IIT Madras Incubation Cell (IITMIC) | C7: Chennai | D7: 2013 | E7: University(IIT Madras) | F7: https://www.iitm.ac.in/research-park/incubation-cell | G7: A total portfolio of 567 startups, reported in April 2026. | H7: 567 | I7: 13 | J7: =H7/I7 -> 43.615385 | K7: =RANK(H7,$H$2:$H$25,0) -> 7 | L7: =RANK(J7,$J$2:$J$25,0) -> 5 | M7: =AVERAGE(K7,L7) -> 6 | N7: =IF(A7<=20,"Yes","No") -> Yes | O7: Over ₹17,000 crore in investor funding, with a combined valuation of about ₹53,000 crore (Dec 2025). Around 190 companies are still operating. | P7: Nodal deep-tech incubation center of IIT Madras. It was incorporated in December 2013 as a Section 8 company with a board and various committees overseeing incubation and seed investments. | R7: https://www.iitm.ac.in/research-park/incubation-cell
A8: =COUNTIF($M$2:$M$25,"<"&M8)+COUNTIFS($M$2:$M$25,M8,$K$2:$K$25,"<"&K8)+1 -> 7 | B8: Startup Village (Kochi) | C8: Kochi (Kalamassery) | D8: 2012 | E8: Public-private partnership incubator | F8: https://www.pupilfirst.org/ | G8: 570+ physical and virtual startups (historical, first three years) | H8: 570 | I8: 14 | J8: =H8/I8 -> 40.714286 | K8: =RANK(H8,$H$2:$H$25,0) -> 6 | L8: =RANK(J8,$J$2:$J$25,0) -> 8 | M8: =AVERAGE(K8,L8) -> 7 | N8: =IF(A8<=20,"Yes","No") -> Yes | O8: Cumulative funding not publicly verified; supported by DST and private-sector contributions | P8: India’s first public-private-partnership technology business incubator. It was set up by Mobme Wireless and Technopark TBI with ₹2.5 crore of DST financial assistance, and began operating in April 2012. | Q8: 570+ is a historical figure for the first three years (physical + virtual); no later figure found. | R8: https://yourstory.com/2015/12/kochi-startup-village
A9: =COUNTIF($M$2:$M$25,"<"&M9)+COUNTIFS($M$2:$M$25,M9,$K$2:$K$25,"<"&K9)+1 -> 8 | B9: WE Hub | C9: Hyderabad | D9: 2018 | E9: Government | F9: https://wehub.telangana.gov.in/ | G9: 342 women-led startups incubated (CEO, Aug 2021). A later tag page says close to 3,180 women-owned startups. | H9: 342 | I9: 8 | J9: =H9/I9 -> 42.75 | K9: =RANK(H9,$H$2:$H$25,0) -> 9 | L9: =RANK(J9,$J$2:$J$25,0) -> 6 | M9: =AVERAGE(K9,L9) -> 7.5 | N9: =IF(A9<=20,"Yes","No") -> Yes | O9: ₹55 crore raised (Aug 2021) | P9: India’s first state-led incubator exclusively for women entrepreneurs, launched by the Telangana government. | Q9: 342 is the Aug-2021 CEO figure; a later page claims ~3,180 women-owned startups. The conservative, dated figure is used. | R9: https://negd.gov.in/isl/Directory/statedata/704
A10: =COUNTIF($M$2:$M$25,"<"&M10)+COUNTIFS($M$2:$M$25,M10,$K$2:$K$25,"<"&K10)+1 -> 9 | B10: a-IDEA (NAARM TBI) | C10: Hyderabad | D10: 2014 | E10: Government research institute (ICAR) | F10: https://aidea.naarm.org.in/ | G10: 300+ nurtured across agriculture and allied sectors (directory). | H10: 300 | I10: 12 | J10: =H10/I10 -> 25 | K10: =RANK(H10,$H$2:$H$25,0) -> 11 | L10: =RANK(J10,$J$2:$J$25,0) -> 10 | M10: =AVERAGE(K10,L10) -> 10.5 | N10: =IF(A10<=20,"Yes","No") -> Yes | O10: SIDBI SEED (up to ₹1 Cr), BIRAC BIG (up to ₹50 lakh), NIDHI PRAYAS (prototype grants). | P10: An agri-business incubator hosted by ICAR-NAARM and supported by DST. | R10: https://aidea.naarm.org.in/
A11: =COUNTIF($M$2:$M$25,"<"&M11)+COUNTIFS($M$2:$M$25,M11,$K$2:$K$25,"<"&K11)+1 -> 10 | B11: Amrita TBI | C11: Amritapuri, Kollam | D11: 2005 | E11: University (Private deemed university), government-supported | F11: https://www.amritatbi.com/ | G11: 320+ startups incubated | H11: 320 | I11: 21 | J11: =H11/I11 -> 15.238095 | K11: =RANK(H11,$H$2:$H$25,0) -> 10 | L11: =RANK(J11,$J$2:$J$25,0) -> 13 | M11: =AVERAGE(K11,L11) -> 11.5 | N11: =IF(A11<=20,"Yes","No") -> Yes | O11: US$330 million raised by incubated startups (approx. ₹2,750 crore) | P11: A non-profit technology business incubator supported by DST and Amrita Vishwa Vidyapeetham. It won the national Best Technology Business Incubator award in 2017. | R11: https://www.amritatbi.com/
A12: =COUNTIF($M$2:$M$25,"<"&M12)+COUNTIFS($M$2:$M$25,M12,$K$2:$K$25,"<"&K12)+1 -> 11 | B12: Marwari Catalysts | C12: Jodhpur | D12: 2019 | E12: Private | F12: https://www.marwaricatalysts.com/home.php | G12: 200+ startups supported | H12: 200 | I12: 7 | J12: =H12/I12 -> 28.571429 | K12: =RANK(H12,$H$2:$H$25,0) -> 14 | L12: =RANK(J12,$J$2:$J$25,0) -> 9 | M12: =AVERAGE(K12,L12) -> 11.5 | N12: =IF(A12<=20,"Yes","No") -> Yes | O12: ₹25 lakh initial investment + up to ₹75 lakh follow-on funding under Thrive; up to ₹1 crore total. | P12: A Jodhpur-based accelerator and venture platform backing startups from Tier-II and Tier-III cities. | R12: https://www.marwaricatalysts.com/home.php
A13: =COUNTIF($M$2:$M$25,"<"&M13)+COUNTIFS($M$2:$M$25,M13,$K$2:$K$25,"<"&K13)+1 -> 12 | B13: TREC-STEP (Tiruchirappalli) | C13: Tiruchirappalli | D13: 1986 | E13: Government-promoted,institute-hosted | F13: https://www.trecstep.com/ | G13: 400+ high-tech startups incubated and graduated | H13: 400 | I13: 40 | J13: =H13/I13 -> 10 | K13: =RANK(H13,$H$2:$H$25,0) -> 8 | L13: =RANK(J13,$J$2:$J$25,0) -> 16 | M13: =AVERAGE(K13,L13) -> 12 | N13: =IF(A13<=20,"Yes","No") -> Yes | O13: ₹50 lakh seed incubation support per eligible startup (historical scheme); BEACON India programme approved for US$25 million in Green Climate Fund support | P13: One of India’s earliest science and technology entrepreneurs parks. It was promoted in 1986 by DST with the Government of Tamil Nadu and NIT Tiruchirappalli as host. | R13: https://www.trecstep.com/
A14: =COUNTIF($M$2:$M$25,"<"&M14)+COUNTIFS($M$2:$M$25,M14,$K$2:$K$25,"<"&K14)+1 -> 13 | B14: GUSEC (Gujarat University Startup Entrepreneurship Council) | C14: Ahmedabad | D14: 2016 | E14: University | F14: https://gusec.edu.in/ | G14: 234 supported, with ₹14 crore revenue and 666 jobs created (about 2020). 600+ per a directory. | H14: 234 | I14: 10 | J14: =H14/I14 -> 23.4 | K14: =RANK(H14,$H$2:$H$25,0) -> 13 | L14: =RANK(J14,$J$2:$J$25,0) -> 11 | M14: =AVERAGE(K14,L14) -> 12 | N14: =IF(A14<=20,"Yes","No") -> Yes | O14: ₹10 crore grant sanctioned to GUSEC by NSTEDB to invest in startups. This is a grant to the incubator, not funding raised by its startups. | P14: A not-for-profit startup support council at Gujarat University. It was set up in February 2016 and is recognised as a NIDHI technology business incubator. | R14: https://gusec.edu.in/
A15: =COUNTIF($M$2:$M$25,"<"&M15)+COUNTIFS($M$2:$M$25,M15,$K$2:$K$25,"<"&K15)+1 -> 14 | B15: SINE (IIT Bombay) | C15: Mumbai | D15: 2004 as a society (pilot from 1999) | E15: University (IIT Bombay) | F15: https://www.sineiitb.org/ | G15: 245 startups, with a collective valuation of $3.56 billion. 81 were being incubated at the time (Jan 2025 report) | H15: 245 | I15: 22 | J15: =H15/I15 -> 11.136364 | K15: =RANK(H15,$H$2:$H$25,0) -> 12 | L15: =RANK(J15,$J$2:$J$25,0) -> 15 | M15: =AVERAGE(K15,L15) -> 13.5 | N15: =IF(A15<=20,"Yes","No") -> Yes | O15: $942 million total (late 2024 / Jan 2025 announcement). | P15: IIT Bombay’s technology business incubator for deep-tech and hardware startups. It began as a pilot in 1999 and became a non-profit society in 2004. | R15: https://www.sineiitb.org/
A16: =COUNTIF($M$2:$M$25,"<"&M16)+COUNTIFS($M$2:$M$25,M16,$K$2:$K$25,"<"&K16)+1 -> 15 | B16: Maker Village | C16: Kochi | D16: 2015 | E16: Government (MeitY) with university hosting. | F16: http://makervillage.in/ | G16: Over 178 to 194+ startups supported (with around 45–178+ tracked depending on the specific cohort or tracking metrics). | H16: 194 | I16: 11 | J16: =H16/I16 -> 17.636364 | K16: =RANK(H16,$H$2:$H$25,0) -> 15 | L16: =RANK(J16,$J$2:$J$25,0) -> 12 | M16: =AVERAGE(K16,L16) -> 13.5 | N16: =IF(A16<=20,"Yes","No") -> Yes | O16: ₹220 Cr raised; ₹46.17 Cr direct support; ₹40 Cr MeitY GENESIS; ₹5 Cr SISFS. | P16: India’s largest electronics hardware incubator. It is a MeitY initiative implemented by IIIT-Trivandrum, with Kerala Startup Mission as supporting partner. | R16: https://www.startupgrantsindia.com/providers/maker-village
A17: =COUNTIF($M$2:$M$25,"<"&M17)+COUNTIFS($M$2:$M$25,M17,$K$2:$K$25,"<"&K17)+1 -> 16 | B17: JioGenNext | C17: Mumbai (Navi Mumbai) | D17: 2013 | E17: Corporate | F17: https://www.jiogennext.com/ | G17: 185 Indian-originated startups supported. 118 alumni raised funding and 73 raised institutional funding. | H17: 185 | I17: 13 | J17: =H17/I17 -> 14.230769 | K17: =RANK(H17,$H$2:$H$25,0) -> 16 | L17: =RANK(J17,$J$2:$J$25,0) -> 14 | M17: =AVERAGE(K17,L17) -> 15 | N17: =IF(A17<=20,"Yes","No") -> Yes | O17: ₹2,600 crore+ raised by 170+ startups (older directory figure). | P17: Reliance’s equity-free corporate accelerator running the Market Access Programme. | R17: https://www.jiogennext.com/
A18: =COUNTIF($M$2:$M$25,"<"&M18)+COUNTIFS($M$2:$M$25,M18,$K$2:$K$25,"<"&K18)+1 -> 17 | B18: JSS ATEB STEP | C18: Bengaluru | D18: 1999 (registered as a society in 2003) | E18: University/College | F18: https://www.jssatebstep.com/ | G18: 150+ as mentioned in official website | H18: 150 | I18: 27 | J18: =H18/I18 -> 5.5555556 | K18: =RANK(H18,$H$2:$H$25,0) -> 17 | L18: =RANK(J18,$J$2:$J$25,0) -> 18 | M18: =AVERAGE(K18,L18) -> 17.5 | N18: =IF(A18<=20,"Yes","No") -> Yes | O18: ₹5Cr+ Funding Raised | P18: A technology business incubator for IoT, AI, healthcare, power, water and agritech. | R18: https://www.jssatebstep.com/
A19: =COUNTIF($M$2:$M$25,"<"&M19)+COUNTIFS($M$2:$M$25,M19,$K$2:$K$25,"<"&K19)+1 -> 18 | B19: IIM Calcutta Innovation Park (IIMCIP) | C19: Kolkata | D19: Incorporated 22 August 2014 as a Section 8 company | E19: University | F19: https://iimcip.org/ | G19: 100+ startups supported and 5,500+ entrepreneurs mentored (directory updated Feb 2026) | H19: 100 | I19: 12 | J19: =H19/I19 -> 8.3333333 | K19: =RANK(H19,$H$2:$H$25,0) -> 19 | L19: =RANK(J19,$J$2:$J$25,0) -> 17 | M19: =AVERAGE(K19,L19) -> 18 | N19: =IF(A19<=20,"Yes","No") -> Yes | O19: ₹26 crore of seed funding provided, and ₹1,946 crore of follow-on funding facilitated. | P19: Incubator of not-for-profit organizations, run by IIM Calcutta, catering to eastern and north-eastern India with emphasis on social entrepreneurship. | Q19: 100+ startups supported (directory, Feb 2026); the 5,500+ entrepreneurs mentored are not startups. | R19: https://iimcip.org/
A20: =COUNTIF($M$2:$M$25,"<"&M20)+COUNTIFS($M$2:$M$25,M20,$K$2:$K$25,"<"&K20)+1 -> 19 | B20: Amity Innovation Incubator | C20: Noida | D20: 2008 | E20: University (Private) | F20: https://www.amity.edu/aii/ | G20: 100+ companies incubated (physical and virtual), 263+ patents filed, and 42 startups founded by Amity faculty and students. | H20: 100 | I20: 18 | J20: =H20/I20 -> 5.5555556 | K20: =RANK(H20,$H$2:$H$25,0) -> 19 | L20: =RANK(J20,$J$2:$J$25,0) -> 18 | M20: =AVERAGE(K20,L20) -> 18.5 | N20: =IF(A20<=20,"Yes","No") -> Yes | O20: Seed funding up to ₹50 lakh; SISFS, NIDHI-SSS, SAMRIDH, AIM and TIDE 2.0; angel/VC investor access. | P20: A university incubator in Noida supported by DST, covering ICT, biotech and nanotechnology. | Q20: "100+" companies incubated used; the separate 42 faculty/student-founded startups are not added. | R20: https://www.amity.edu/aii/
A21: =COUNTIF($M$2:$M$25,"<"&M21)+COUNTIFS($M$2:$M$25,M21,$K$2:$K$25,"<"&K21)+1 -> 20 | B21: Agri-Business Incubator (ABI-ICRISAT) | C21: Patancheru,Hyderabad | D21: 2003 | E21: International research institute (CGIAR),DST-supported | F21: https://www.icrisat.org/services/business-incubation | G21: 118 supported, of which 98 have graduated, with 3,000+ direct jobs created (Nov 2022). | H21: 118 | I21: 23 | J21: =H21/I21 -> 5.1304348 | K21: =RANK(H21,$H$2:$H$25,0) -> 18 | L21: =RANK(J21,$J$2:$J$25,0) -> 20 | M21: =AVERAGE(K21,L21) -> 19 | N21: =IF(A21<=20,"Yes","No") -> Yes | O21: Over USD 57 million in follow-on funding. | P21: An agri-tech incubator hosted by ICRISAT, the international dryland-crops research institute. It was set up in 2003 with DST support. | R21: https://www.icrisat.org/services/business-incubation
A22: =COUNTIF($M$2:$M$25,"<"&M22)+COUNTIFS($M$2:$M$25,M22,$K$2:$K$25,"<"&K22)+1 -> 21 | B22: BITS Pilani TBI | C22: Pilani, Rajasthan | D22: 2004 | E22: University-affiliated/ Government incubator | F22: https://www.bits-pilani.ac.in/pilani/technology-business-incubator/ | G22: 75+ startups supported by the Pilani incubator; 300+ startups formed by BITS students and alumni across the broader ecosystem. | H22: 75 | I22: 22 | J22: =H22/I22 -> 3.4090909 | K22: =RANK(H22,$H$2:$H$25,0) -> 21 | L22: =RANK(J22,$J$2:$J$25,0) -> 21 | M22: =AVERAGE(K22,L22) -> 21 | N22: =IF(A22<=20,"Yes","No") -> No | O22: Up to ₹50 lakh per startup (seed funding; programme-dependent) | P22: Technology Business Incubator at BITS Pilani backed by DST. The Pilani center began with one startup in 2005. | R22: https://www.bits-pilani.ac.in/pilani/technology-business-incubator/
A23: =COUNTIF($M$2:$M$25,"<"&M23)+COUNTIFS($M$2:$M$25,M23,$K$2:$K$25,"<"&K23)+1 -> 22 | B23: Target Accelerator Program (Target India) | C23: Bengaluru | D23: 2014 | E23: Corporate accelerator/incubation programme | F23: https://accelerators.target.com/ | G23: 36 startups mentored by February 2019; 30 graduates reported across the first five cohorts in July 2018. | H23: 36 | I23: 12 | J23: =H23/I23 -> 3 | K23: =RANK(H23,$H$2:$H$25,0) -> 22 | L23: =RANK(J23,$J$2:$J$25,0) -> 22 | M23: =AVERAGE(K23,L23) -> 22 | N23: =IF(A23<=20,"Yes","No") -> No | O23: Up to US$30,000 per startup was reported in the initial 2013 programme announcement. | P23: A corporate accelerator by US retailer Target, focused on retail technology. Launched in Bengaluru in January 2014. | R23: https://accelerators.target.com/
A24: =COUNTIF($M$2:$M$25,"<"&M24)+COUNTIFS($M$2:$M$25,M24,$K$2:$K$25,"<"&K24)+1 -> 23 | B24: Sathyabama TBI | C24: Chennai | D24: 2012 | E24: University(private deemed) | F24: https://www.sathyabama.ac.in/ | G24: 34 startups launched through the Sathyabama Innovation Council; | H24: 34 | I24: 14 | J24: =H24/I24 -> 2.4285714 | K24: =RANK(H24,$H$2:$H$25,0) -> 23 | L24: =RANK(J24,$J$2:$J$25,0) -> 24 | M24: =AVERAGE(K24,L24) -> 23.5 | N24: =IF(A24<=20,"Yes","No") -> No | O24: ₹5.25 crore under the Startup India Seed Fund Scheme (SISFS) to support startups | P24: A DST-supported incubator. It is run through a non-profit Section 8 company. Its report calls it the first TBI in India to focus on the Blue Economy. | R24: https://www.sathyabama.ac.in/
A25: =COUNTIF($M$2:$M$25,"<"&M25)+COUNTIFS($M$2:$M$25,M25,$K$2:$K$25,"<"&K25)+1 -> 24 | B25: thinQbate | C25: Mumbai | D25: 2016 | E25: Private | F25: http://thinqbate.com/ | G25: 29+ investments recorded in Crunchbase | H25: 29 | I25: 10 | J25: =H25/I25 -> 2.9 | K25: =RANK(H25,$H$2:$H$25,0) -> 24 | L25: =RANK(J25,$J$2:$J$25,0) -> 23 | M25: =AVERAGE(K25,L25) -> 23.5 | N25: =IF(A25<=20,"Yes","No") -> No | O25: $75K for 5-15% equity (a directory’s terms, undated).Not publicly disclosed | P25: A community-based startup incubator in Mumbai that takes equity and offers space, mentors and bridge financing. | R25: https://www.crunchbase.com/organization/thinqbate

Sheet All Candidates (32)
A1: Name | B1: Category (research sheet) | C1: Decision | D1: Reason | E1: Final Rank (if eligible)
A2: T-Hub | B2: Incubator/ accelerator | C2: Included - Top 20 | D2: Runs its own incubation/acceleration programme for startups; scored on both methods. | E2: =IFERROR(INDEX('Top 20 Ranking'!$A$2:$A$25,MATCH(A2,'Top 20 Ranking'!$B$2:$B$25,0)),"-") -> 3
A3: NSRCEL (IIM Bangalore) | B3: Incubator/ accelerator | C3: Included - Top 20 | D3: Runs its own incubation/acceleration programme for startups; scored on both methods. | E3: =IFERROR(INDEX('Top 20 Ranking'!$A$2:$A$25,MATCH(A3,'Top 20 Ranking'!$B$2:$B$25,0)),"-") -> 2
A4: CIIE.CO (IIM Ahmedabad; now IIMA Ventures) | B4: Incubator/ accelerator | C4: Included - Top 20 | D4: Runs its own incubation/acceleration programme for startups; scored on both methods. | E4: =IFERROR(INDEX('Top 20 Ranking'!$A$2:$A$25,MATCH(A4,'Top 20 Ranking'!$B$2:$B$25,0)),"-") -> 5
A5: IIT Madras Incubation Cell (IITMIC) | B5: Incubator/ accelerator | C5: Included - Top 20 | D5: Runs its own incubation/acceleration programme for startups; scored on both methods. | E5: =IFERROR(INDEX('Top 20 Ranking'!$A$2:$A$25,MATCH(A5,'Top 20 Ranking'!$B$2:$B$25,0)),"-") -> 6
A6: Kerala Startup Mission (KSUM) | B6: Incubator/ accelerator | C6: Included - Top 20 | D6: Runs its own incubation/acceleration programme for startups; scored on both methods. | E6: =IFERROR(INDEX('Top 20 Ranking'!$A$2:$A$25,MATCH(A6,'Top 20 Ranking'!$B$2:$B$25,0)),"-") -> 1
A7: IIM Calcutta Innovation Park (IIMCIP) | B7: Incubator/ accelerator | C7: Included - Top 20 | D7: Runs its own incubation/acceleration programme for startups; scored on both methods. | E7: =IFERROR(INDEX('Top 20 Ranking'!$A$2:$A$25,MATCH(A7,'Top 20 Ranking'!$B$2:$B$25,0)),"-") -> 18
A8: BITS Pilani TBI | B8: Incubator/ accelerator | C8: Eligible - ranked 21-24 (outside Top 20) | D8: Runs its own incubation/acceleration programme for startups; scored on both methods. | E8: =IFERROR(INDEX('Top 20 Ranking'!$A$2:$A$25,MATCH(A8,'Top 20 Ranking'!$B$2:$B$25,0)),"-") -> 21
A9: SINE (IIT Bombay) | B9: Incubator/ accelerator | C9: Included - Top 20 | D9: Runs its own incubation/acceleration programme for startups; scored on both methods. | E9: =IFERROR(INDEX('Top 20 Ranking'!$A$2:$A$25,MATCH(A9,'Top 20 Ranking'!$B$2:$B$25,0)),"-") -> 14
A10: Maker Village | B10: Incubator/ accelerator | C10: Included - Top 20 | D10: Runs its own incubation/acceleration programme for startups; scored on both methods. | E10: =IFERROR(INDEX('Top 20 Ranking'!$A$2:$A$25,MATCH(A10,'Top 20 Ranking'!$B$2:$B$25,0)),"-") -> 15
A11: Startup Village (Kochi) | B11: Incubator/ accelerator | C11: Included - Top 20 | D11: Runs its own incubation/acceleration programme for startups; scored on both methods. | E11: =IFERROR(INDEX('Top 20 Ranking'!$A$2:$A$25,MATCH(A11,'Top 20 Ranking'!$B$2:$B$25,0)),"-") -> 7
A12: WE Hub | B12: Incubator/ accelerator | C12: Included - Top 20 | D12: Runs its own incubation/acceleration programme for startups; scored on both methods. | E12: =IFERROR(INDEX('Top 20 Ranking'!$A$2:$A$25,MATCH(A12,'Top 20 Ranking'!$B$2:$B$25,0)),"-") -> 8
A13: GUSEC (Gujarat University Startup Entrepreneurship Council) | B13: Incubator/ accelerator | C13: Included - Top 20 | D13: Runs its own incubation/acceleration programme for startups; scored on both methods. | E13: =IFERROR(INDEX('Top 20 Ranking'!$A$2:$A$25,MATCH(A13,'Top 20 Ranking'!$B$2:$B$25,0)),"-") -> 13
... A33: AdvantEdge Founders | B33: Investment-fund-led | C33: Excluded - investment fund / angel network | D33: Primary activity is investing capital (VC / AIF / angel fund), not running an incubator. Sensitivity check in Method sheet. | E33: =IFERROR(INDEX('Top 20 Ranking'!$A$2:$A$25,MATCH(A33,'Top 20 Ranking'!$B$2:$B$25,0)),"-") -> -

Sheet Method
A1: Search methodology
A2: Route A - registries and directories | B2: Government/ecosystem listings of recognised incubators (e.g. national startup directories, DST/NIDHI-type programme lists, curated grant-provider directories) used to find candidates.
A3: Route B - open web | B3: Each incubator's own website, news coverage (e.g. YourStory), press releases and company databases (e.g. Crunchbase) used to find candidates missing from directories and to read current size figures.
A4: Candidate pool | B4: 32 organisations were collected from the two routes and recorded in the 'All Candidates' sheet.
A5: Eligibility rule | B5: An organisation is ranked only if it runs its own incubation or acceleration programme for startups. Investment funds / angel networks (6) and funding schemes / umbrella networks (2) are excluded. 24 organisations remain.
A6: Ranking methodology
A7: Definition of 'largest' | B7: Number of startups supported. Funding raised, revenue or floor space were not used because they are reported inconsistently or not at all.
A8: Methodology 1 - scale | B8: Rank by cumulative startups supported (higher = larger).
A9: Methodology 2 - throughput | B9: Rank by startups per year = cumulative startups / years operating. This stops very old incubators winning purely on age.
A10: Combination | B10: Final rank = rank of the average of the two ranks; ties go to the better Method 1 rank. The 20 best are the Top 20.
A11: Robustness | B11: The same 20 organisations appear in the top 20 under Method 1 alone and under Method 2 alone; only the order changes. The cut-off is clear: the 21st organisation (BITS Pilani TBI) has 75 startups against 100-118 for ranks 18-20.
A12: Sensitivity to the eligibility rule | B12: If the 6 investment-fund entries were allowed in, Peak XV Surge, 100X.VC and FAAD Network would enter the top 20 and displace IIMCIP, Amity Innovation Incubator and ABI-ICRISAT. The top 8 would be unchanged and the incubators ranked 9-17 would move down by at most three places.
A13: Limitations
A14: Self-reported figures | B14: Counts come from incubators, press or directories, are not audited, and use different definitions (registered, supported, accelerated, incubated). See the 'Data note' column.
A15: Different dates | B15: Figures are from different years (2021-2026). Years operating is counted to 2026 for everyone, which understates intake for incubators whose figure is old (e.g. WE Hub, Startup Village, Zone Startups).
A16: Judgement calls | B16: KSUM (a state agency that runs incubation) is kept; ACIC (a scheme funding many centres) is excluded. Peak XV Surge is excluded as a VC-run programme. Changing these calls is a one-cell edit in the Decision column plus a re-sort.
